quda/__init__.py
quda/qdf/__init__.py
quda/qdf/errors.py
quda/qdf/expr.py
quda/qdf/qdf.py
quda/qdf/udf/__init__.py
quda/qdf/udf/base_udf.py
quda/qdf/udf/cs_udf.py
quda/qdf/udf/d_udf.py
quda/qdf/udf/itd_udf.py
quda/qdf/udf/ts_udf.py
quda/store/__init__.py
quda/store/database.py
quda/store/parse.py
quda/updater/__init__.py
quda/updater/base.py
quda/updater/updater.py
quda_core-1.0.3.dist-info/METADATA
quda_core-1.0.3.dist-info/WHEEL
quda_core-1.0.3.dist-info/top_level.txt
quda_core-1.0.3.dist-info/RECORD
