Metadata-Version: 2.4
Name: quda-core
Version: 1.0.3
License-Expression: MIT
Requires-Python: >=3.12
Requires-Dist: clickhouse-df>=0.1.5
Requires-Dist: dynaconf>=3.2.11
Requires-Dist: lark>=1.2.2
Requires-Dist: numpy>=2.3.1
Requires-Dist: polars>=1.31.0
Requires-Dist: sqlparse>=0.5.3
Requires-Dist: xcals>=0.0.4
Requires-Dist: ygo>=1.1.4
